{
  "employees": [
    {
      "id": "b9e9",
      "empno": "",
      "empname": "",
      "city": "",
      "salary": 0
    },
    {
      "id": "3918",
      "empno": "43",
      "empname": "jgk",
      "city": "bhopal",
      "salary": 2500
    },
    {
      "id": "9173",
      "empno": "43",
      "empname": "jgk",
      "city": "kjhk",
      "salary": 0
    },
    {
      "id": "9484",
      "empno": "458",
      "empname": "priya",
      "city": "bhopal",
      "salary": 25000
    },
    {
      "id": "0c2c",
      "empno": "458",
      "empname": "priya",
      "city": "bhopal",
      "salary": 25000
    },
    {
      "id": "663e",
      "empno": "458",
      "empname": "priya",
      "city": "bhopal",
      "salary": 25000
    },
    {
      "id": "88f9",
      "empno": "112",
      "name": "riya",
      "city": "hosangabad",
      "salary": 25000
    },
    {
      "id": "26dc",
      "empno": "112",
      "name": "riya",
      "city": "hosangabad",
      "salary": 25000
    },
    {
      "id": "3d54",
      "empno": "",
      "name": "",
      "city": "",
      "salary": 0
    },
    {
      "id": "6b8a",
      "empno": "112",
      "empname": "riya",
      "city": "hosangabad",
      "salary": 25000
    },
    {
      "id": "882f",
      "empno": "116",
      "empname": "aman",
      "city": "indore",
      "salary": 2560
    },
    {
      "id": "265d",
      "empno": "116",
      "empname": "aman",
      "city": "indore",
      "salary": 2560
    },
    {
      "id": "55f1",
      "empno": "43",
      "name": "priya katare",
      "city": "hosangabad",
      "salary": "25000"
    },
    {
      "id": "c7f4",
      "empno": "43",
      "name": "priya katare",
      "city": "hosangabad",
      "salary": "25000"
    },
    {
      "id": "9775",
      "empno": "43",
      "name": "priya katare",
      "city": "hosangabad",
      "salary": "25000"
    },
    {
      "id": "384b",
      "empno": "43",
      "name": "priya katare",
      "city": "hosangabad",
      "salary": "25000"
    },
    {
      "id": "4ca8",
      "empno": "43",
      "name": "priya katare",
      "city": "hosangabad",
      "salary": "25000"
    }
  ]
}